{
	"id": "F250",
	"name": "歐索林酸",
	"licenses": [
		{
			"許可證號": "02120",
			"化學成分": "5-ethyl-5,8-dihydro-8-oxo[1,3]dioxolo[4,5-g]quinoline-7-carboxylic acid",
			"廠牌名稱": "住友金星",
			"國外原製造廠商": "SUMIKA AGRO MANUFACTURING LTD. SHOBARA FACTORY",
			"有效期限": "107/08/30",
			"廠商名稱": "台灣住友化學股份有限公司"
		}
	],
	"英文名稱": "OXOLINIC ACID",
	"作用機制": "[FRAC] 31, A4",
	"廠牌名稱": "OXOLINIC ACID",
	"通過日期": "089-03-20",
	"usages": [
		{
			"劑型": "WP",
			"含量": "20.000",
			"混合": "",
			"作物名稱": "檬果",
			"病蟲名稱": "黑斑病",
			"每公頃每次用量": "",
			"稀釋倍數": "1000",
			"使用時期": "發病初期",
			"施藥間隔": "7",
			"施用次數": "4-5",
			"安全採收期": "12",
			"核准日期": "89-08-31",
			"原始登記廠商名稱": "台灣住友商事股份有限公司",
			"施藥方法": "",
			"注意事項": "1.標示加註對具呼吸中等毒性。 2.加註魚毒警告標誌，勿使用於「飲用水水源水質保護區」或「飲用水取水口一定距離內之地區」。 3.本劑試驗時加展著劑「較好配」3000倍",
			"備註": ""
		}
	]
}