{
	"id": "I241",
	"name": "伽瑪賽洛寧",
	"licenses": [
		{
			"許可證號": "02353",
			"化學成分": "(S)-α-cyano-3-phenoxybenzyl (Z)-(1R,3R)-3-(2-chloro-3,3,3-trifluoroprop-1-enyl)-2,2-dimethylcyclopropanecarboxylate",
			"廠牌名稱": "速落寧",
			"國外原製造廠商": "CHEMINOVA A/S",
			"有效期限": "108/04/11",
			"廠商名稱": "台灣科麥農有限公司"
		}
	],
	"英文名稱": "GAMMA-CYHALOTHRIN",
	"通過日期": "094-02-16",
	"usages": [
		{
			"劑型": "CS",
			"含量": "1.500",
			"混合": "",
			"作物名稱": "茄子",
			"病蟲名稱": "二點小綠葉蟬",
			"每公頃每次用量": "0.25-0.5公升",
			"稀釋倍數": "2000",
			"使用時期": "害蟲發生時",
			"施藥間隔": "7",
			"施用次數": "-",
			"安全採收期": "6",
			"核准日期": "94-02-16",
			"原始登記廠商名稱": "台灣道禮股份有限公司",
			"施藥方法": "",
			"注意事項": "1.具水生物劇毒性。2.魚毒警告標誌。3.勿使用於「飲用水水源水質保護區」及「飲用水取水口一定距離內之地區」。",
			"備註": ""
		}
	]
}