{
	"id": "I252",
	"name": "剋安勃",
	"licenses": [
		{
			"許可證號": "02678",
			"化學成分": "3-bromo-4’-chloro-1-(3-chloro-2-pyridyl)-2’-methyl-6’-(methylcarbamoyl)pyrazole-5-carboxanilide",
			"廠牌名稱": "絲奄奄",
			"國外原製造廠商": "E. I. DU PONT DE NEMOURS & COMPANY - VALDOSTA MANUFACTURING CENTER",
			"有效期限": "108/05/04",
			"廠商名稱": "台灣杜邦股份有限公司"
		},
		{
			"許可證號": "02795",
			"化學成分": "3-bromo-4’-chloro-1-(3-chloro-2-pyridyl)-2’-methyl-6’-(methylcarbamoyl)pyrazole-5-carboxanilide",
			"廠牌名稱": "金靈海",
			"國外原製造廠商": "GOWAN MILLING COMPANY, L.L.C.",
			"有效期限": "105/04/26",
			"廠商名稱": "台灣杜邦股份有限公司"
		}
	],
	"英文名稱": "CHLORANTRANILIPROLE"
}