{"id":"H002","name":"丁拉免速隆","農藥代號":"H002","中文名稱":"丁拉免速隆","licenses":[{"許可證號":"03745","廠牌名稱":"龍無草–丁","國外原製造廠商":"","有效期限":"103/10/10","廠商名稱":"大勝化學工業股份有限公司"},{"許可證號":"03746","廠牌名稱":"億草除","國外原製造廠商":"","有效期限":"103/10/10","廠商名稱":"億豐農化廠股份有限公司"}],"英文名稱":"BUTACHLOR + BENSULFURON-METHYL","化學成分":"(1)METHYL α-(4,6-DIMETHOXYPYRIMIDIN-2- YLCARBAMOYLSULFAMOYL)-o-TOLUATE(BENSULFURON-METHYL )…..0.083%                                             (2)N-BUTOXYMETHYL-2-CHLORO-2’,6’-DIETHYLACETANILIDE(BUTACHLOR)…..2.5%","通過日期":"078-09-21","uses":[{"劑型":"GR","含量":"2.583","混合":"A","作物名稱":"移植本田","病蟲名稱":"雜草","每公頃每次用量":"30公斤","稀釋倍數":"","使用時期":"插秧後","施藥間隔":"-","施用次數":"-","安全採收期":"-","核准日期":"-  -","原始登記廠商名稱":"","施藥方法":"","注意事項":"","備註":""}]}